pixiuquant/__init__.py
pixiuquant-0.0.2.dist-info/METADATA
pixiuquant-0.0.2.dist-info/WHEEL
pixiuquant-0.0.2.dist-info/top_level.txt
pixiuquant-0.0.2.dist-info/RECORD
